bkp/__init__.py
bkp/__main__.py
bkp/action_backup.py
bkp/action_info.py
bkp/action_restore.py
bkp/config.py
bkp/exceptions.py
bkp/fsop.py
bkp/resources.py
bkp/tarop.py
bkp/terminal.py
bkp/timestamp.py
bkp-1.0.0.dist-info/METADATA
bkp-1.0.0.dist-info/WHEEL
bkp-1.0.0.dist-info/entry_points.txt
bkp-1.0.0.dist-info/RECORD
