Metadata-Version: 2.1
Name: bkp
Version: 1.0.0
Summary: Creates backups of your files and directories.
Home-page: https://github.com/gergelyk/bkp
License: MIT
Keywords: backup
Author: Grzegorz Krason
Author-email: grzegorz.krason@gmail.com
Requires-Python: >=3.8,<4.0
Classifier: License :: OSI Approved :: MIT License
Classifier: Operating System :: POSIX
Classifier: Operating System :: Unix
Classifier: Programming Language :: Python
Classifier: Programming Language :: Python :: 3
Classifier: Programming Language :: Python :: 3.8
Classifier: Programming Language :: Python :: 3.9
Classifier: Programming Language :: Python :: 3.10
Classifier: Programming Language :: Python :: 3.11
Classifier: Topic :: Desktop Environment
Classifier: Topic :: Office/Business
Classifier: Topic :: System
Classifier: Topic :: Utilities
Requires-Dist: click (>=8.1.7,<9.0.0)
Project-URL: Repository, https://github.com/gergelyk/bkp
